checkpoint/__init__.py
checkpoint/__main__.py
checkpoint/crypt.py
checkpoint/io.py
checkpoint/readers.py
checkpoint/sequences.py
checkpoint/utils.py
pycheckpoint-1.3.dist-info/LICENSE.txt
pycheckpoint-1.3.dist-info/METADATA
pycheckpoint-1.3.dist-info/WHEEL
pycheckpoint-1.3.dist-info/entry_points.txt
pycheckpoint-1.3.dist-info/top_level.txt
pycheckpoint-1.3.dist-info/RECORD
