Metadata-Version: 2.1
Name: pycheckpoint
Version: 1.3
Summary: Create restore points in your projects
Home-page: https://github.com/antrikshmisri/checkpoint
Author: Antriksh Misri
Author-email: antrikshmisri@gmail.com
License: MIT
Keywords: checkpoint,cli,executable
Platform: UNKNOWN
Classifier: Development Status :: 5 - Production/Stable
Classifier: Intended Audience :: Education
Classifier: Operating System :: Microsoft :: Windows :: Windows 10
Classifier: License :: OSI Approved :: MIT License
Classifier: Programming Language :: Python :: 3
License-File: LICENSE.txt
Requires-Dist: cryptography (==3.4.7)
Requires-Dist: joblib (==1.0.1)
Requires-Dist: numpy (==1.20.3)
Requires-Dist: pytest (==6.2.4)
